rafi/__init__.py
rafi/app.py
rafi-0.2.1.dist-info/LICENSE
rafi-0.2.1.dist-info/WHEEL
rafi-0.2.1.dist-info/METADATA
rafi-0.2.1.dist-info/RECORD
