Metadata-Version: 2.1
Name: rafi
Version: 0.2.1
Summary: A tiny route dispatcher for Google Cloud Functions.
Home-page: http://github.com/dabio/rafi
License: MIT
Author: Danilo Braband
Author-email: dbraband@gmail.com
Requires-Python: >=3.7,<4.0
Classifier: Development Status :: 3 - Alpha
Classifier: Intended Audience :: Developers
Classifier: License :: OSI Approved :: MIT License
Classifier: Programming Language :: Python :: 3
Classifier: Programming Language :: Python :: 3.7
Project-URL: Repository, http://github.com/dabio/rafi
